pipe_utils/__init__.py
pipe_utils/_types.py
pipe_utils/curry.py
pipe_utils/iterables.py
pipe_utils/mappings.py
pipe_utils/override.py
pipe_utils/pipe.py
pipe_utils/values.py
pipe_utils-0.5.0.dist-info/LICENSE
pipe_utils-0.5.0.dist-info/METADATA
pipe_utils-0.5.0.dist-info/WHEEL
pipe_utils-0.5.0.dist-info/top_level.txt
pipe_utils-0.5.0.dist-info/RECORD
