Metadata-Version: 2.1
Name: pipe-utils
Version: 0.5.0
Summary: Python with pipes, utils, and pipe utils
License: MIT License
Project-URL: repository, https://github.com/James-Ansley/pipe-utils
Project-URL: documentation, https://pipe-utils.rtfd.io/
Classifier: Development Status :: 5 - Production/Stable
Classifier: Topic :: Utilities
Classifier: Programming Language :: Python :: 3
Classifier: License :: OSI Approved :: MIT License
Requires-Python: >=3.12
License-File: LICENSE
Requires-Dist: Deprecated ~=1.2.13
